{
 "info": [
  [
   0,
   1,
   15,
   "OTHER",
   "The Pointy End"
  ],
  [
   0,
   62,
   77,
   "OTHER",
   "Game of Thrones"
  ],
  [
   2,
   18,
   22,
   "OTHER",
   "June"
  ],
  [
   3,
   37,
   47,
   "OTHER",
   "George R.R"
  ],
  [
   4,
   0,
   6,
   "OTHER",
   "Martin"
  ],
  [
   4,
   23,
   37,
   "OTHER",
   "Daniel Minahan"
  ]
 ],
 "plot": [
  [
   0,
   20,
   25,
   "OTHER",
   "Ned\u02bcs"
  ],
  [
   0,
   35,
   40,
   "OTHER",
   "Syrio"
  ],
  [
   0,
   45,
   49,
   "OTHER",
   "Arya"
  ],
  [
   0,
   67,
   76,
   "OTHER",
   "Lannister"
  ],
  [
   0,
   91,
   97,
   "OTHER",
   "Cersei"
  ],
  [
   0,
   110,
   115,
   "OTHER",
   "Sansa"
  ],
  [
   1,
   0,
   4,
   "OTHER",
   "Robb"
  ],
  [
   1,
   53,
   68,
   "OTHER",
   "Tywin Lannister"
  ],
  [
   2,
   0,
   6,
   "OTHER",
   "Tyrion"
  ],
  [
   3,
   0,
   3,
   "OTHER",
   "Jon"
  ],
  [
   3,
   18,
   36,
   "OTHER",
   "Ser Alliser Thorne"
  ],
  [
   3,
   87,
   91,
   "OTHER",
   "Wall"
  ],
  [
   3,
   0,
   3,
   "OTHER",
   "Jon"
  ],
  [
   4,
   0,
   4,
   "OTHER",
   "Dany"
  ],
  [
   4,
   50,
   58,
   "OTHER",
   "Westeros"
  ],
  [
   4,
   64,
   71,
   "OTHER",
   "Drogo\u02bcs"
  ],
  [
   4,
   91,
   99,
   "OTHER",
   "Dothraki"
  ]
 ],
 "summary/Across the Narrow Sea": [
  [
   0,
   0,
   10,
   "OTHER",
   "Khal Drogo"
  ],
  [
   0,
   23,
   27,
   "OTHER",
   "Mago"
  ],
  [
   1,
   0,
   8,
   "OTHER",
   "Daenerys"
  ],
  [
   1,
   15,
   20,
   "OTHER",
   "Drogo"
  ],
  [
   2,
   3,
   8,
   "OTHER",
   "Essos"
  ],
  [
   2,
   10,
   20,
   "OTHER",
   "Khal Drogo"
  ],
  [
   2,
   54,
   65,
   "OTHER",
   "Iron Throne"
  ],
  [
   2,
   106,
   116,
   "OTHER",
   "Narrow Sea"
  ],
  [
   3,
   0,
   12,
   "OTHER",
   "The Dothraki"
  ],
  [
   3,
   31,
   37,
   "OTHER",
   "Lhazar"
  ],
  [
   3,
   79,
   91,
   "OTHER",
   "Vaes Dothrak"
  ],
  [
   4,
   158,
   166,
   "OTHER",
   "Westeros"
  ],
  [
   5,
   0,
   9,
   "OTHER",
   "Ser Jorah"
  ],
  [
   5,
   44,
   52,
   "OTHER",
   "Daenerys"
  ],
  [
   5,
   101,
   109,
   "OTHER",
   "Dothraki"
  ],
  [
   6,
   0,
   12,
   "OTHER",
   "The Dothraki"
  ],
  [
   6,
   4,
   12,
   "OTHER",
   "Dothraki"
  ],
  [
   6,
   88,
   96,
   "OTHER",
   "Dothraki"
  ],
  [
   8,
   44,
   54,
   "OTHER",
   "Khal Drogo"
  ],
  [
   9,
   19,
   27,
   "OTHER",
   "Daenerys"
  ],
  [
   10,
   42,
   47,
   "OTHER",
   "Drogo"
  ],
  [
   11,
   0,
   10,
   "OTHER",
   "Khal Drogo"
  ],
  [
   11,
   43,
   47,
   "OTHER",
   "Mago"
  ],
  [
   12,
   0,
   5,
   "OTHER",
   "Drogo"
  ],
  [
   13,
   7,
   12,
   "OTHER",
   "Drogo"
  ],
  [
   13,
   187,
   192,
   "OTHER",
   "Drogo"
  ],
  [
   13,
   40,
   48,
   "OTHER",
   "Daenerys"
  ],
  [
   13,
   128,
   142,
   "OTHER",
   "Mirri Maz Duur"
  ],
  [
   13,
   7,
   12,
   "OTHER",
   "Drogo"
  ],
  [
   13,
   187,
   192,
   "OTHER",
   "Drogo"
  ]
 ],
 "summary/At the Lannister Camp": [
  [
   0,
   0,
   5,
   "OTHER",
   "Kevan"
  ],
  [
   0,
   10,
   25,
   "OTHER",
   "Tywin Lannister"
  ],
  [
   0,
   32,
   38,
   "OTHER",
   "Tyrion"
  ],
  [
   1,
   0,
   6,
   "OTHER",
   "Tyrion"
  ],
  [
   1,
   8,
   13,
   "OTHER",
   "Bronn"
  ],
  [
   1,
   15,
   21,
   "OTHER",
   "Shagga"
  ],
  [
   1,
   71,
   80,
   "OTHER",
   "Lannister"
  ],
  [
   1,
   112,
   121,
   "OTHER",
   "Lannister"
  ],
  [
   1,
   101,
   121,
   "OTHER",
   "Lord Tywin Lannister"
  ],
  [
   1,
   139,
   148,
   "OTHER",
   "Ser Kevan"
  ],
  [
   1,
   173,
   178,
   "OTHER",
   "Stark"
  ],
  [
   1,
   216,
   220,
   "OTHER",
   "Neck"
  ],
  [
   2,
   0,
   5,
   "OTHER",
   "Tywin"
  ],
  [
   3,
   0,
   5,
   "OTHER",
   "Tywin"
  ],
  [
   3,
   122,
   127,
   "OTHER",
   "Tywin"
  ],
  [
   3,
   49,
   55,
   "OTHER",
   "Shagga"
  ],
  [
   3,
   75,
   81,
   "OTHER",
   "Tyrion"
  ],
  [
   3,
   151,
   157,
   "OTHER",
   "Tyrion"
  ],
  [
   3,
   0,
   5,
   "OTHER",
   "Tywin"
  ],
  [
   3,
   122,
   127,
   "OTHER",
   "Tywin"
  ],
  [
   3,
   75,
   81,
   "OTHER",
   "Tyrion"
  ],
  [
   3,
   151,
   157,
   "OTHER",
   "Tyrion"
  ]
 ],
 "summary/At the Wall": [
  [
   0,
   0,
   3,
   "OTHER",
   "Jon"
  ],
  [
   0,
   8,
   11,
   "OTHER",
   "Sam"
  ],
  [
   0,
   22,
   34,
   "OTHER",
   "Castle Black"
  ],
  [
   0,
   0,
   3,
   "OTHER",
   "Jon"
  ],
  [
   0,
   8,
   11,
   "OTHER",
   "Sam"
  ],
  [
   1,
   45,
   57,
   "OTHER",
   "Benjen Stark"
  ],
  [
   1,
   83,
   96,
   "OTHER",
   "Jafer Flowers"
  ],
  [
   1,
   101,
   106,
   "OTHER",
   "Othor"
  ],
  [
   2,
   60,
   63,
   "OTHER",
   "Sam"
  ],
  [
   2,
   60,
   63,
   "OTHER",
   "Sam"
  ],
  [
   3,
   0,
   3,
   "OTHER",
   "Jon"
  ],
  [
   3,
   22,
   36,
   "OTHER",
   "Sworn Brothers"
  ],
  [
   3,
   42,
   69,
   "OTHER",
   "Lord Commander Jeor Mormont"
  ],
  [
   3,
   114,
   127,
   "OTHER",
   "Maester Aemon"
  ],
  [
   3,
   0,
   3,
   "OTHER",
   "Jon"
  ],
  [
   3,
   114,
   127,
   "OTHER",
   "Maester Aemon"
  ],
  [
   4,
   0,
   3,
   "OTHER",
   "Jon"
  ],
  [
   4,
   19,
   26,
   "OTHER",
   "Mormont"
  ],
  [
   4,
   61,
   67,
   "OTHER",
   "Eddard"
  ],
  [
   4,
   0,
   3,
   "OTHER",
   "Jon"
  ],
  [
   5,
   63,
   66,
   "OTHER",
   "Jon"
  ],
  [
   5,
   92,
   99,
   "OTHER",
   "Mormont"
  ],
  [
   5,
   144,
   157,
   "OTHER",
   "Night's Watch"
  ],
  [
   5,
   63,
   66,
   "OTHER",
   "Jon"
  ],
  [
   6,
   5,
   8,
   "OTHER",
   "Jon"
  ],
  [
   6,
   97,
   100,
   "OTHER",
   "Jon"
  ],
  [
   6,
   44,
   51,
   "OTHER",
   "Mormont"
  ],
  [
   6,
   5,
   8,
   "OTHER",
   "Jon"
  ],
  [
   6,
   97,
   100,
   "OTHER",
   "Jon"
  ],
  [
   6,
   5,
   8,
   "OTHER",
   "Jon"
  ],
  [
   6,
   97,
   100,
   "OTHER",
   "Jon"
  ],
  [
   7,
   10,
   24,
   "OTHER",
   "Alliser Thorne"
  ],
  [
   7,
   32,
   35,
   "OTHER",
   "Jon"
  ],
  [
   7,
   32,
   35,
   "OTHER",
   "Jon"
  ],
  [
   8,
   0,
   3,
   "OTHER",
   "Jon"
  ],
  [
   8,
   90,
   93,
   "OTHER",
   "Jon"
  ],
  [
   8,
   44,
   50,
   "OTHER",
   "Thorne"
  ],
  [
   8,
   68,
   73,
   "OTHER",
   "Grenn"
  ],
  [
   8,
   78,
   81,
   "OTHER",
   "Pyp"
  ],
  [
   8,
   0,
   3,
   "OTHER",
   "Jon"
  ],
  [
   8,
   90,
   93,
   "OTHER",
   "Jon"
  ],
  [
   8,
   0,
   3,
   "OTHER",
   "Jon"
  ],
  [
   8,
   90,
   93,
   "OTHER",
   "Jon"
  ],
  [
   9,
   0,
   17,
   "OTHER",
   "Commander Mormont"
  ],
  [
   9,
   54,
   57,
   "OTHER",
   "Jon"
  ],
  [
   9,
   54,
   57,
   "OTHER",
   "Jon"
  ],
  [
   10,
   12,
   15,
   "OTHER",
   "Jon"
  ],
  [
   10,
   40,
   45,
   "OTHER",
   "Ghost"
  ],
  [
   10,
   12,
   15,
   "OTHER",
   "Jon"
  ],
  [
   11,
   17,
   20,
   "OTHER",
   "Jon"
  ],
  [
   11,
   82,
   85,
   "OTHER",
   "Jon"
  ],
  [
   11,
   50,
   64,
   "OTHER",
   "Lord Commander"
  ],
  [
   11,
   17,
   20,
   "OTHER",
   "Jon"
  ],
  [
   11,
   82,
   85,
   "OTHER",
   "Jon"
  ],
  [
   11,
   146,
   162,
   "OTHER",
   "Night's Watchman"
  ],
  [
   11,
   17,
   20,
   "OTHER",
   "Jon"
  ],
  [
   11,
   82,
   85,
   "OTHER",
   "Jon"
  ],
  [
   12,
   7,
   10,
   "OTHER",
   "Jon"
  ],
  [
   12,
   7,
   10,
   "OTHER",
   "Jon"
  ],
  [
   13,
   0,
   7,
   "OTHER",
   "Mormont"
  ],
  [
   14,
   0,
   3,
   "OTHER",
   "Jon"
  ],
  [
   14,
   10,
   17,
   "OTHER",
   "Mormont"
  ],
  [
   14,
   0,
   3,
   "OTHER",
   "Jon"
  ],
  [
   16,
   0,
   3,
   "OTHER",
   "Sam"
  ],
  [
   16,
   74,
   87,
   "OTHER",
   "White Walkers"
  ],
  [
   16,
   0,
   3,
   "OTHER",
   "Sam"
  ],
  [
   17,
   13,
   17,
   "OTHER",
   "Wall"
  ],
  [
   17,
   59,
   66,
   "OTHER",
   "Walkers"
  ]
 ],
 "summary/In King's Landing": [
  [
   0,
   0,
   9,
   "OTHER",
   "Lannister"
  ],
  [
   0,
   47,
   52,
   "OTHER",
   "Stark"
  ],
  [
   1,
   0,
   5,
   "OTHER",
   "Sansa"
  ],
  [
   1,
   10,
   23,
   "OTHER",
   "Septa Mordane"
  ],
  [
   2,
   28,
   37,
   "OTHER",
   "Lannister"
  ],
  [
   2,
   55,
   69,
   "OTHER",
   "Sandor Clegane"
  ],
  [
   2,
   71,
   84,
   "OTHER",
   "Septa Mordane"
  ],
  [
   2,
   91,
   96,
   "OTHER",
   "Sansa"
  ],
  [
   3,
   9,
   15,
   "OTHER",
   "Sandor"
  ],
  [
   3,
   38,
   43,
   "OTHER",
   "Sansa"
  ],
  [
   4,
   0,
   11,
   "OTHER",
   "Syrio Forel"
  ],
  [
   4,
   22,
   37,
   "OTHER",
   "Ser Meryn Trant"
  ],
  [
   4,
   42,
   51,
   "OTHER",
   "Lannister"
  ],
  [
   5,
   5,
   14,
   "OTHER",
   "Lannister"
  ],
  [
   5,
   43,
   76,
   "OTHER",
   "Ser Meryn Trant of the Kingsguard"
  ],
  [
   5,
   115,
   126,
   "OTHER",
   "Syrio Forel"
  ],
  [
   5,
   131,
   135,
   "OTHER",
   "Arya"
  ],
  [
   6,
   0,
   5,
   "OTHER",
   "Syrio"
  ],
  [
   6,
   12,
   16,
   "OTHER",
   "Arya"
  ],
  [
   6,
   84,
   88,
   "OTHER",
   "Arya"
  ],
  [
   6,
   39,
   50,
   "OTHER",
   "Lord Eddard"
  ],
  [
   6,
   62,
   71,
   "OTHER",
   "Lannister"
  ],
  [
   6,
   12,
   16,
   "OTHER",
   "Arya"
  ],
  [
   6,
   84,
   88,
   "OTHER",
   "Arya"
  ],
  [
   7,
   71,
   76,
   "OTHER",
   "Syrio"
  ],
  [
   8,
   9,
   13,
   "OTHER",
   "Arya"
  ],
  [
   8,
   38,
   43,
   "OTHER",
   "Trant"
  ],
  [
   8,
   75,
   97,
   "OTHER",
   "First Sword of Braavos"
  ],
  [
   9,
   0,
   5,
   "OTHER",
   "Syrio"
  ],
  [
   10,
   0,
   4,
   "OTHER",
   "Arya"
  ],
  [
   10,
   115,
   125,
   "OTHER",
   "Winterfell"
  ],
  [
   11,
   48,
   54,
   "OTHER",
   "Needle"
  ],
  [
   12,
   0,
   4,
   "OTHER",
   "Arya"
  ],
  [
   13,
   1,
   5,
   "OTHER",
   "Arya"
  ],
  [
   13,
   34,
   42,
   "OTHER",
   "Red Keep"
  ],
  [
   14,
   36,
   40,
   "OTHER",
   "Arya"
  ],
  [
   14,
   66,
   72,
   "OTHER",
   "Needle"
  ],
  [
   16,
   0,
   5,
   "OTHER",
   "Varys"
  ],
  [
   16,
   13,
   25,
   "OTHER",
   "Eddard Stark"
  ],
  [
   17,
   23,
   29,
   "OTHER",
   "Eddard"
  ],
  [
   17,
   38,
   50,
   "OTHER",
   "Littlefinger"
  ],
  [
   17,
   93,
   99,
   "OTHER",
   "Cersei"
  ],
  [
   18,
   0,
   6,
   "OTHER",
   "Eddard"
  ],
  [
   18,
   41,
   47,
   "OTHER",
   "Cersei"
  ],
  [
   18,
   65,
   71,
   "OTHER",
   "Robert"
  ],
  [
   19,
   0,
   5,
   "OTHER",
   "Varys"
  ],
  [
   19,
   20,
   26,
   "OTHER",
   "Eddard"
  ],
  [
   19,
   73,
   79,
   "OTHER",
   "Eddard"
  ],
  [
   19,
   57,
   68,
   "OTHER",
   "King Robert"
  ],
  [
   19,
   20,
   26,
   "OTHER",
   "Eddard"
  ],
  [
   19,
   73,
   79,
   "OTHER",
   "Eddard"
  ],
  [
   20,
   0,
   5,
   "OTHER",
   "Varys"
  ],
  [
   20,
   26,
   33,
   "OTHER",
   "Catelyn"
  ],
  [
   20,
   55,
   61,
   "OTHER",
   "Tyrion"
  ],
  [
   20,
   96,
   102,
   "OTHER",
   "Starks"
  ],
  [
   20,
   135,
   141,
   "OTHER",
   "Eddard"
  ],
  [
   21,
   5,
   11,
   "OTHER",
   "Eddard"
  ],
  [
   21,
   48,
   53,
   "OTHER",
   "Varys"
  ],
  [
   22,
   15,
   21,
   "OTHER",
   "Eddard"
  ],
  [
   22,
   27,
   32,
   "OTHER",
   "Varys"
  ],
  [
   22,
   54,
   59,
   "OTHER",
   "Varys"
  ],
  [
   22,
   27,
   32,
   "OTHER",
   "Varys"
  ],
  [
   22,
   54,
   59,
   "OTHER",
   "Varys"
  ],
  [
   24,
   0,
   6,
   "OTHER",
   "Cersei"
  ],
  [
   24,
   60,
   81,
   "OTHER",
   "Grand Maester Pycelle"
  ],
  [
   24,
   83,
   88,
   "OTHER",
   "Varys"
  ],
  [
   24,
   94,
   106,
   "OTHER",
   "Littlefinger"
  ],
  [
   24,
   115,
   120,
   "OTHER",
   "Sansa"
  ],
  [
   25,
   16,
   21,
   "OTHER",
   "Sansa"
  ],
  [
   25,
   59,
   63,
   "OTHER",
   "Robb"
  ],
  [
   25,
   107,
   114,
   "OTHER",
   "Joffrey"
  ],
  [
   26,
   14,
   20,
   "OTHER",
   "Eddard"
  ],
  [
   26,
   69,
   77,
   "OTHER",
   "Northern"
  ],
  [
   27,
   0,
   5,
   "OTHER",
   "Sansa"
  ],
  [
   28,
   10,
   22,
   "OTHER",
   "King Joffrey"
  ],
  [
   28,
   42,
   50,
   "OTHER",
   "Red Keep"
  ],
  [
   29,
   0,
   11,
   "OTHER",
   "Janos Slynt"
  ],
  [
   29,
   30,
   40,
   "OTHER",
   "City Watch"
  ],
  [
   29,
   56,
   73,
   "OTHER",
   "Lord of Harrenhal"
  ],
  [
   30,
   0,
   6,
   "OTHER",
   "Cersei"
  ],
  [
   30,
   22,
   41,
   "OTHER",
   "Ser Barristan Selmy"
  ],
  [
   30,
   57,
   67,
   "OTHER",
   "Kingsguard"
  ],
  [
   31,
   0,
   5,
   "OTHER",
   "Selmy"
  ],
  [
   31,
   94,
   99,
   "OTHER",
   "Selmy"
  ],
  [
   31,
   37,
   47,
   "OTHER",
   "Kingsguard"
  ],
  [
   31,
   68,
   75,
   "OTHER",
   "Joffrey"
  ],
  [
   31,
   0,
   5,
   "OTHER",
   "Selmy"
  ],
  [
   31,
   94,
   99,
   "OTHER",
   "Selmy"
  ],
  [
   32,
   0,
   5,
   "OTHER",
   "Selmy"
  ],
  [
   32,
   63,
   77,
   "OTHER",
   "Lord Commander"
  ],
  [
   32,
   96,
   111,
   "OTHER",
   "Jaime Lannister"
  ],
  [
   33,
   0,
   5,
   "OTHER",
   "Varys"
  ],
  [
   33,
   21,
   26,
   "OTHER",
   "Selmy"
  ],
  [
   33,
   242,
   249,
   "OTHER",
   "Joffrey"
  ],
  [
   33,
   328,
   338,
   "OTHER",
   "Kingsguard"
  ],
  [
   34,
   0,
   5,
   "OTHER",
   "Sansa"
  ],
  [
   34,
   11,
   18,
   "OTHER",
   "Joffrey"
  ],
  [
   35,
   0,
   7,
   "OTHER",
   "Joffrey"
  ],
  [
   35,
   67,
   73,
   "OTHER",
   "Eddard"
  ],
  [
   36,
   0,
   5,
   "OTHER",
   "Sansa"
  ]
 ],
 "summary/In the North": [
  [
   0,
   25,
   35,
   "OTHER",
   "Winterfell"
  ],
  [
   0,
   66,
   71,
   "OTHER",
   "North"
  ],
  [
   1,
   0,
   4,
   "OTHER",
   "Robb"
  ],
  [
   1,
   28,
   33,
   "OTHER",
   "Sansa"
  ],
  [
   1,
   37,
   51,
   "OTHER",
   "King's Landing"
  ],
  [
   1,
   84,
   96,
   "OTHER",
   "King Joffrey"
  ],
  [
   2,
   0,
   13,
   "OTHER",
   "Maester Luwin"
  ],
  [
   2,
   71,
   76,
   "OTHER",
   "Queen"
  ],
  [
   3,
   0,
   4,
   "OTHER",
   "Robb"
  ],
  [
   3,
   96,
   101,
   "OTHER",
   "North"
  ],
  [
   3,
   134,
   144,
   "OTHER",
   "Winterfell"
  ],
  [
   5,
   3,
   13,
   "OTHER",
   "Winterfell"
  ],
  [
   5,
   15,
   19,
   "OTHER",
   "Robb"
  ],
  [
   6,
   0,
   9,
   "OTHER",
   "Jon Umber"
  ],
  [
   6,
   124,
   130,
   "OTHER",
   "Glover"
  ],
  [
   6,
   0,
   3,
   "OTHER",
   "Jon"
  ],
  [
   7,
   13,
   17,
   "OTHER",
   "Robb"
  ],
  [
   7,
   211,
   215,
   "OTHER",
   "Robb"
  ],
  [
   7,
   61,
   71,
   "OTHER",
   "Lannisters"
  ],
  [
   7,
   86,
   94,
   "OTHER",
   "Greatjon"
  ],
  [
   7,
   148,
   159,
   "OTHER",
   "House Stark"
  ],
  [
   7,
   13,
   17,
   "OTHER",
   "Robb"
  ],
  [
   7,
   211,
   215,
   "OTHER",
   "Robb"
  ],
  [
   7,
   227,
   236,
   "OTHER",
   "Grey Wind"
  ],
  [
   8,
   0,
   4,
   "OTHER",
   "Robb"
  ],
  [
   8,
   116,
   124,
   "OTHER",
   "Greatjon"
  ],
  [
   8,
   167,
   175,
   "OTHER",
   "Greatjon"
  ],
  [
   8,
   116,
   124,
   "OTHER",
   "Greatjon"
  ],
  [
   8,
   167,
   175,
   "OTHER",
   "Greatjon"
  ],
  [
   9,
   0,
   12,
   "OTHER",
   "The Greatjon"
  ],
  [
   9,
   45,
   49,
   "OTHER",
   "Robb"
  ],
  [
   9,
   83,
   87,
   "OTHER",
   "Bran"
  ],
  [
   10,
   0,
   4,
   "OTHER",
   "Robb"
  ],
  [
   10,
   77,
   81,
   "OTHER",
   "Robb"
  ],
  [
   10,
   22,
   26,
   "OTHER",
   "Bran"
  ],
  [
   10,
   34,
   40,
   "OTHER",
   "Rickon"
  ],
  [
   10,
   0,
   4,
   "OTHER",
   "Robb"
  ],
  [
   10,
   77,
   81,
   "OTHER",
   "Robb"
  ],
  [
   11,
   0,
   4,
   "OTHER",
   "Bran"
  ],
  [
   11,
   54,
   58,
   "OTHER",
   "Osha"
  ],
  [
   11,
   77,
   99,
   "OTHER",
   "Old Gods of the Forest"
  ],
  [
   11,
   77,
   85,
   "OTHER",
   "Old Gods"
  ],
  [
   11,
   161,
   169,
   "OTHER",
   "Old Gods"
  ],
  [
   12,
   21,
   26,
   "OTHER",
   "South"
  ],
  [
   12,
   112,
   117,
   "OTHER",
   "South"
  ],
  [
   12,
   70,
   79,
   "OTHER",
   "Weirwoods"
  ],
  [
   12,
   112,
   123,
   "OTHER",
   "Southerners"
  ],
  [
   13,
   24,
   29,
   "OTHER",
   "Hodor"
  ],
  [
   13,
   96,
   100,
   "OTHER",
   "Osha"
  ],
  [
   13,
   154,
   158,
   "OTHER",
   "Bran"
  ],
  [
   14,
   9,
   13,
   "OTHER",
   "Bran"
  ],
  [
   16,
   26,
   30,
   "OTHER",
   "Robb"
  ],
  [
   17,
   0,
   7,
   "OTHER",
   "Catelyn"
  ],
  [
   17,
   12,
   29,
   "OTHER",
   "Ser Rodrik Cassel"
  ],
  [
   17,
   40,
   44,
   "OTHER",
   "Robb"
  ],
  [
   17,
   59,
   63,
   "OTHER",
   "Neck"
  ],
  [
   18,
   0,
   4,
   "OTHER",
   "Robb"
  ],
  [
   19,
   0,
   7,
   "OTHER",
   "Catelyn"
  ],
  [
   20,
   10,
   14,
   "OTHER",
   "Robb"
  ],
  [
   21,
   41,
   44,
   "OTHER",
   "Ned"
  ],
  [
   21,
   46,
   51,
   "OTHER",
   "Sansa"
  ],
  [
   21,
   57,
   61,
   "OTHER",
   "Arya"
  ],
  [
   21,
   85,
   100,
   "OTHER",
   "Tywin Lannister"
  ],
  [
   22,
   10,
   14,
   "OTHER",
   "Robb"
  ],
  [
   22,
   112,
   117,
   "OTHER",
   "Tywin"
  ],
  [
   22,
   136,
   141,
   "OTHER",
   "Jaime"
  ],
  [
   22,
   159,
   167,
   "OTHER",
   "Riverrun"
  ],
  [
   23,
   10,
   15,
   "OTHER",
   "Jaime"
  ],
  [
   23,
   40,
   71,
   "OTHER",
   "Green Fork of the River Trident"
  ],
  [
   23,
   105,
   110,
   "OTHER",
   "Twins"
  ],
  [
   23,
   164,
   180,
   "OTHER",
   "Lord Walder Frey"
  ],
  [
   24,
   2,
   11,
   "OTHER",
   "Lannister"
  ],
  [
   24,
   35,
   39,
   "OTHER",
   "Robb"
  ],
  [
   24,
   63,
   73,
   "OTHER",
   "Lord Tywin"
  ],
  [
   24,
   95,
   103,
   "OTHER",
   "Northern"
  ]
 ],
 "summary/In the Vale": [
  [
   0,
   7,
   12,
   "OTHER",
   "Eyrie"
  ],
  [
   0,
   14,
   21,
   "OTHER",
   "Catelyn"
  ],
  [
   0,
   38,
   42,
   "OTHER",
   "Lysa"
  ],
  [
   0,
   54,
   58,
   "OTHER",
   "Lysa"
  ],
  [
   0,
   38,
   42,
   "OTHER",
   "Lysa"
  ],
  [
   0,
   54,
   58,
   "OTHER",
   "Lysa"
  ],
  [
   0,
   95,
   101,
   "OTHER",
   "Eddard"
  ],
  [
   0,
   176,
   180,
   "OTHER",
   "Vale"
  ],
  [
   1,
   101,
   110,
   "OTHER",
   "Jon Arryn"
  ],
  [
   1,
   112,
   116,
   "OTHER",
   "Lysa"
  ],
  [
   1,
   153,
   157,
   "OTHER",
   "Vale"
  ],
  [
   1,
   218,
   222,
   "OTHER",
   "Vale"
  ],
  [
   1,
   153,
   157,
   "OTHER",
   "Vale"
  ],
  [
   1,
   218,
   222,
   "OTHER",
   "Vale"
  ],
  [
   1,
   252,
   256,
   "OTHER",
   "Lord"
  ],
  [
   1,
   101,
   104,
   "OTHER",
   "Jon"
  ],
  [
   2,
   0,
   6,
   "OTHER",
   "Tyrion"
  ],
  [
   2,
   11,
   16,
   "OTHER",
   "Bronn"
  ],
  [
   2,
   54,
   58,
   "OTHER",
   "Vale"
  ],
  [
   2,
   141,
   147,
   "OTHER",
   "Shagga"
  ],
  [
   3,
   42,
   48,
   "OTHER",
   "Tyrion"
  ],
  [
   3,
   107,
   122,
   "OTHER",
   "House Lannister"
  ],
  [
   3,
   142,
   153,
   "OTHER",
   "House Arryn"
  ],
  [
   4,
   79,
   90,
   "OTHER",
   "House Arryn"
  ],
  [
   4,
   130,
   134,
   "OTHER",
   "Vale"
  ],
  [
   5,
   31,
   37,
   "OTHER",
   "Tyrion"
  ],
  [
   5,
   42,
   47,
   "OTHER",
   "Bronn"
  ],
  [
   5,
   76,
   85,
   "OTHER",
   "Lannister"
  ]
 ]
}